IdeaSearch/.gitignore
IdeaSearch/__init__.py
IdeaSearch/babel.cfg
IdeaSearch/evaluator.py
IdeaSearch/ideasearcher.py
IdeaSearch/island.py
IdeaSearch/sampler.py
IdeaSearch/typing.py
IdeaSearch/utils.py
IdeaSearch/locales/ideasearch.pot
IdeaSearch/locales/en/LC_MESSAGES/ideasearch.mo
IdeaSearch/locales/en/LC_MESSAGES/ideasearch.po
IdeaSearch/locales/zh_CN/LC_MESSAGES/ideasearch.mo
IdeaSearch/locales/zh_CN/LC_MESSAGES/ideasearch.po
ideasearch-0.1.1.dist-info/METADATA
ideasearch-0.1.1.dist-info/WHEEL
ideasearch-0.1.1.dist-info/licenses/LICENSE
ideasearch-0.1.1.dist-info/RECORD
