Metadata-Version: 2.4
Name: IdeaSearch
Version: 0.1.1
Summary: IdeaSearch Framework - An AI-powered research idea generation and optimization system
Project-URL: Homepage, https://github.com/IdeaSearch/IdeaSearch-framework
Project-URL: Documentation, https://ideasearch-framework.readthedocs.io
Project-URL: Repository, https://github.com/ideasearch/ideasearch-framework
Project-URL: Bug Tracker, https://github.com/ideasearch/ideasearch-framework/issues
Project-URL: Changelog, https://github.com/ideasearch/ideasearch-framework/blob/main/CHANGELOG.md
Author-email: parkcai <sun_retailer@163.com>
License-Expression: MIT
License-File: LICENSE
Keywords: artificial-intelligence,evolutionary-algorithm,idea-generation,llm,optimization,research
Classifier: Development Status :: 3 - Alpha
Classifier: Intended Audience :: Developers
Classifier: Intended Audience :: Science/Research
Classifier: License :: OSI Approved :: MIT License
Classifier: Operating System :: OS Independent
Classifier: Programming Language :: Python :: 3
Classifier: Programming Language :: Python :: 3.8
Classifier: Programming Language :: Python :: 3.9
Classifier: Programming Language :: Python :: 3.10
Classifier: Programming Language :: Python :: 3.11
Classifier: Programming Language :: Python :: 3.12
Classifier: Topic :: Scientific/Engineering :: Artificial Intelligence
Classifier: Topic :: Software Development :: Libraries :: Python Modules
Requires-Python: >=3.8
Requires-Dist: matplotlib>=3.5.0
Requires-Dist: numpy>=1.21.0
Requires-Dist: pywheels>=0.3.6
